LICENSE.txt
README.md
setup.cfg
setup.py
pyNDL/Assets.py
pyNDL/Colors.py
pyNDL/Components.py
pyNDL/DataHandler.py
pyNDL/Node.py
pyNDL/NodePrefabs.py
pyNDL/NodeSelector.py
pyNDL/Pin.py
pyNDL/Rope.py
pyNDL/TextBox.py
pyNDL/ThreadedProcess.py
pyNDL/VariableAndFunction.py
pyNDL/__init__.py
pyNDL/libs_install.py
pyNDL/pyNDL_.py
pyNDL/Assets/Images/Cross.png
pyNDL/Assets/Images/GoBackArrow.png
pyNDL/Prefabs/List.py
pyNDL/Prefabs/Numpy.py
pyNDL/Prefabs/Operations.py
pyNDL/Prefabs/Pillow.py
pyNDL/Prefabs/PythonBasic.py
pyNDL/Prefabs/VarAndFunc.py
python_NDL.egg-info/PKG-INFO
python_NDL.egg-info/SOURCES.txt
python_NDL.egg-info/dependency_links.txt
python_NDL.egg-info/requires.txt
python_NDL.egg-info/top_level.txt