Metadata-Version: 2.1
Name: python-NDL
Version: 0.4
Summary: A nodal interface for python
Home-page: https://github.com/merwynnn/pyNDL
Download-URL: https://github.com/merwynnn/pyNDL/archive/refs/tags/v_04.tar.gz
Author: Louis Gambardella
Author-email: louis.gambardella03@gmail.com
License: MIT
Keywords: Nodal,Language,pyNDL,Blueprint
Classifier: Development Status :: 3 - Alpha
Classifier: Intended Audience :: Developers
Classifier: Topic :: Software Development :: Build Tools
Classifier: License :: OSI Approved :: MIT License
Classifier: Programming Language :: Python :: 3
Classifier: Programming Language :: Python :: 3.4
Classifier: Programming Language :: Python :: 3.5
Classifier: Programming Language :: Python :: 3.6
Classifier: Programming Language :: Python :: 3.7
Classifier: Programming Language :: Python :: 3.8
Classifier: Programming Language :: Python :: 3.9
Classifier: Programming Language :: Python :: 3.10
Classifier: Programming Language :: Python :: 3.11
License-File: LICENSE.txt
